uiform/__init__.py
uiform/_resource.py
uiform/client.py
uiform/py.typed
uiform/_utils/__init__.py
uiform/_utils/ai_models.py
uiform/_utils/benchmarking copy.py
uiform/_utils/benchmarking.py
uiform/_utils/chat.py
uiform/_utils/display.py
uiform/_utils/json_schema.py
uiform/_utils/mime.py
uiform/_utils/responses.py
uiform/_utils/stream_context_managers.py
uiform/_utils/usage/__init__.py
uiform/_utils/usage/usage.py
uiform/resources/__init__.py
uiform/resources/evals.py
uiform/resources/files.py
uiform/resources/finetuning.py
uiform/resources/jsonlUtils.py
uiform/resources/models.py
uiform/resources/openai_example.py
uiform/resources/prompt_optimization.py
uiform/resources/schemas.py
uiform/resources/usage.py
uiform/resources/consensus/__init__.py
uiform/resources/consensus/client.py
uiform/resources/consensus/completions.py
uiform/resources/consensus/completions_stream.py
uiform/resources/consensus/responses.py
uiform/resources/consensus/responses_stream.py
uiform/resources/deployments/__init__.py
uiform/resources/deployments/client.py
uiform/resources/deployments/endpoints.py
uiform/resources/deployments/links.py
uiform/resources/deployments/logs.py
uiform/resources/deployments/mailboxes.py
uiform/resources/deployments/outlook.py
uiform/resources/deployments/tests.py
uiform/resources/documents/__init__.py
uiform/resources/documents/client.py
uiform/resources/documents/extractions.py
uiform/resources/secrets/__init__.py
uiform/resources/secrets/client.py
uiform/resources/secrets/external_api_keys.py
uiform/resources/secrets/webhook.py
uiform/types/__init__.py
uiform/types/ai_models.py
uiform/types/chat.py
uiform/types/completions.py
uiform/types/consensus.py
uiform/types/evals.py
uiform/types/events.py
uiform/types/extractions.py
uiform/types/logs.py
uiform/types/mime.py
uiform/types/modalities.py
uiform/types/pagination.py
uiform/types/standards.py
uiform/types/db/__init__.py
uiform/types/db/annotations.py
uiform/types/db/files.py
werose-0.0.33.dist-info/METADATA
werose-0.0.33.dist-info/WHEEL
werose-0.0.33.dist-info/top_level.txt
werose-0.0.33.dist-info/RECORD
